README.md
setup.cfg
setup.py
text_stream/__init__.py
text_stream.egg-info/PKG-INFO
text_stream.egg-info/SOURCES.txt
text_stream.egg-info/dependency_links.txt
text_stream.egg-info/top_level.txt
text_stream/tests/__init__.py
text_stream/tests/test_text_stream.py