Metadata-Version: 1.0
Name: text-stream
Version: 0.2.0
Summary: A package for streaming text data model
Home-page: https://github.com/singularitti/text_stream
Author: Qi Zhang
Author-email: qz2280@columbia.edu
License: MIT
Platform: UNKNOWN
